pythonrpc_pyserver/__init__.py
pythonrpc_pyserver/server.py
pythonrpc_pyserver-0.0.2.dist-info/METADATA
pythonrpc_pyserver-0.0.2.dist-info/WHEEL
pythonrpc_pyserver-0.0.2.dist-info/top_level.txt
pythonrpc_pyserver-0.0.2.dist-info/RECORD
